sioba_subprocess/__init__.py
sioba_subprocess/interface/__init__.py
sioba_subprocess/interface/subprocess/__init__.py
sioba_subprocess/interface/subprocess/posix.py
sioba_subprocess/interface/subprocess/windows.py
sioba_subprocess/utils.py
sioba_subprocess-0.4.20250928.dist-info/WHEEL
sioba_subprocess-0.4.20250928.dist-info/entry_points.txt
sioba_subprocess-0.4.20250928.dist-info/METADATA
sioba_subprocess-0.4.20250928.dist-info/RECORD
