Metadata-Version: 2.3
Name: sioba-subprocess
Version: 0.4.20250928
Summary: Sioba Subprocess IO Interface layer
Author: Aki Mimoto
Author-email: Aki Mimoto <aki@bako.ca>
License: MIT License
Classifier: License :: OSI Approved :: MIT License
Requires-Dist: sioba>=0.6
Requires-Dist: loguru>=0.7.2
Requires-Dist: pywinpty>=2.0.4 ; sys_platform == 'win32'
Requires-Python: >=3.10
